Metadata-Version: 2.4
Name: datafix
Version: 0.0.1
Summary: descr
Author: Hannes
Project-URL: Homepage, https://github.com/hannesdelbeke/datafix
Keywords: dcc,app,application,pipeline
Classifier: Programming Language :: Python :: 3.7
Requires-Python: >=3.4
Requires-Dist: importlib-metadata; python_version < "3.7"
